[
    {
        "link": "https://www.seminovosmovida.com.br/veiculo/detalhe/SUV/Renault/Duster/1240382",
        "title": "Renault Duster",
        "version": "Intense Plus 1.6 16v Flex Aut.",
        "details": "2024/2025 • 35.398 KM • São Paulo Eliseu de Almeida, SP",
        "old_price": null,
        "new_price": "R$ 112.300",
        "parcela": "Entrada + parcelas a partir de R$ 1.663*"
    },
    {
        "link": "https://www.seminovosmovida.com.br/veiculo/detalhe/SUV/Renault/Duster/1240380",
        "title": "Renault Duster",
        "version": "Intense Plus 1.6 16v Flex Aut.",
        "details": "2024/2025 • 38.390 KM • São Paulo Aricanduva, SP",
        "old_price": null,
        "new_price": "R$ 112.300",
        "parcela": "Entrada + parcelas a partir de R$ 1.663*"
    },
    {
        "link": "https://www.seminovosmovida.com.br/veiculo/detalhe/SUV/Renault/Duster/1240405",
        "title": "Renault Duster",
        "version": "Intense Plus 1.6 16v Flex Aut.",
        "details": "2024/2025 • 39.430 KM • São Paulo Vila Guilherme, SP",
        "old_price": null,
        "new_price": "R$ 112.300",
        "parcela": "Entrada + parcelas a partir de R$ 1.663*"
    },
    {
        "link": "https://www.seminovosmovida.com.br/veiculo/detalhe/SUV/Renault/Duster/1240315",
        "title": "Renault Duster",
        "version": "Intense Plus 1.6 16v Flex Aut.",
        "details": "2024/2025 • 32.954 KM • São Paulo Ermano Marchetti, SP",
        "old_price": null,
        "new_price": "R$ 112.300",
        "parcela": "Entrada + parcelas a partir de R$ 1.663*"
    },
    {
        "link": "https://www.seminovosmovida.com.br/veiculo/detalhe/SUV/Hyundai/Creta/1163452",
        "title": "Hyundai Creta",
        "version": "Action 1.6 16v Flex Aut.",
        "details": "2024/2025 • 28.040 KM • São Paulo Santana, SP",
        "old_price": null,
        "new_price": "R$ 112.400",
        "parcela": "Entrada + parcelas a partir de R$ 1.664*"
    },
    {
        "link": "https://www.seminovosmovida.com.br/veiculo/detalhe/SUV/Volkswagen/T-Cross/922010",
        "title": "Volkswagen T-Cross",
        "version": "Comfor. 200 Tsi 1.0 Flex 5p Aut.",
        "details": "2022/2023 • 64.324 KM • São Paulo Nações Unidas, SP",
        "old_price": null,
        "new_price": "R$ 112.400",
        "parcela": "Entrada + parcelas a partir de R$ 1.664*"
    },
    {
        "link": "https://www.seminovosmovida.com.br/veiculo/detalhe/SUV/Hyundai/Creta/1177553",
        "title": "Hyundai Creta",
        "version": "Action 1.6 16v Flex Aut.",
        "details": "2024/2025 • 25.302 KM • São Paulo São Miguel, SP",
        "old_price": null,
        "new_price": "R$ 112.400",
        "parcela": "Entrada + parcelas a partir de R$ 1.664*"
    },
    {
        "link": "https://www.seminovosmovida.com.br/veiculo/detalhe/Sedan/Hyundai/Hb20S/1270274",
        "title": "Hyundai Hb20S",
        "version": "Limited 1.0 Tb Flex 12v Aut.",
        "details": "2025/2026 • 27.388 KM • Bauru, SP",
        "old_price": null,
        "new_price": "R$ 112.500",
        "parcela": "Entrada + parcelas a partir de R$ 1.666*"
    },
    {
        "link": "https://www.seminovosmovida.com.br/veiculo/detalhe/SUV/Hyundai/Creta/1163656",
        "title": "Hyundai Creta",
        "version": "Action 1.6 16v Flex Aut.",
        "details": "2024/2025 • 32.169 KM • São Paulo Gastão Vidigal, SP",
        "old_price": null,
        "new_price": "R$ 112.500",
        "parcela": "Entrada + parcelas a partir de R$ 1.666*"
    },
    {
        "link": "https://www.seminovosmovida.com.br/veiculo/detalhe/SUV/Nissan/Kicks/1262208",
        "title": "Nissan Kicks",
        "version": "Play Active Plus 1.6 16v Flex Aut.",
        "details": "2025/2025 • 26.777 KM • Curitiba Floriano, PR",
        "old_price": null,
        "new_price": "R$ 112.500",
        "parcela": "Entrada + parcelas a partir de R$ 1.666*"
    },
    {
        "link": "https://www.seminovosmovida.com.br/veiculo/detalhe/SUV/Nissan/Kicks/1240025",
        "title": "Nissan Kicks",
        "version": "Sense 1.6 16v Flex Aut.",
        "details": "2024/2024 • 10.140 KM • Belém Senador, PA",
        "old_price": null,
        "new_price": "R$ 112.500",
        "parcela": "Entrada + parcelas a partir de R$ 1.666*"
    },
    {
        "link": "https://www.seminovosmovida.com.br/veiculo/detalhe/SUV/Volkswagen/T-Cross/1127218",
        "title": "Volkswagen T-Cross",
        "version": "200 Tsi 1.0 Flex 12v 5p Aut.",
        "details": "2024/2024 • 57.658 KM • São Paulo Itaim Paulista, SP",
        "old_price": null,
        "new_price": "R$ 112.500",
        "parcela": "Entrada + parcelas a partir de R$ 1.666*"
    },
    {
        "link": "https://www.seminovosmovida.com.br/veiculo/detalhe/SUV/Volkswagen/T-Cross/1124554",
        "title": "Volkswagen T-Cross",
        "version": "200 Tsi 1.0 Flex 12v 5p Aut.",
        "details": "2024/2024 • 50.713 KM • São José do Rio Preto, SP",
        "old_price": null,
        "new_price": "R$ 112.500",
        "parcela": "Entrada + parcelas a partir de R$ 1.666*"
    },
    {
        "link": "https://www.seminovosmovida.com.br/veiculo/detalhe/Hatch/Volkswagen/Polo/1206400",
        "title": "Volkswagen Polo",
        "version": "Highline Tsi 1.0 Flex 12v Aut.",
        "details": "2024/2025 • 16.117 KM • Rio de Janeiro Campo Grande, RJ",
        "old_price": null,
        "new_price": "R$ 112.500",
        "parcela": "Entrada + parcelas a partir de R$ 1.666*"
    },
    {
        "link": "https://www.seminovosmovida.com.br/veiculo/detalhe/SUV/Hyundai/Creta/1148749",
        "title": "Hyundai Creta",
        "version": "Action 1.6 16v Flex Aut.",
        "details": "2024/2025 • 36.728 KM • São Bernardo do Campo, SP",
        "old_price": null,
        "new_price": "R$ 112.500",
        "parcela": "Entrada + parcelas a partir de R$ 1.666*"
    },
    {
        "link": "https://www.seminovosmovida.com.br/veiculo/detalhe/Sedan/Hyundai/Hb20S/1269807",
        "title": "Hyundai Hb20S",
        "version": "Limited 1.0 Tb Flex 12v Aut.",
        "details": "2025/2026 • 29.265 KM • Santo André, SP",
        "old_price": null,
        "new_price": "R$ 112.500",
        "parcela": "Entrada + parcelas a partir de R$ 1.666*"
    },
    {
        "link": "https://www.seminovosmovida.com.br/veiculo/detalhe/SUV/Volkswagen/T-Cross/1127303",
        "title": "Volkswagen T-Cross",
        "version": "200 Tsi 1.0 Flex 12v 5p Aut.",
        "details": "2024/2024 • 58.967 KM • Taubaté, SP",
        "old_price": null,
        "new_price": "R$ 112.500",
        "parcela": "Entrada + parcelas a partir de R$ 1.666*"
    },
    {
        "link": "https://www.seminovosmovida.com.br/veiculo/detalhe/SUV/Volkswagen/T-Cross/1127274",
        "title": "Volkswagen T-Cross",
        "version": "200 Tsi 1.0 Flex 12v 5p Aut.",
        "details": "2024/2024 • 56.391 KM • Jundiaí, SP",
        "old_price": null,
        "new_price": "R$ 112.500",
        "parcela": "Entrada + parcelas a partir de R$ 1.666*"
    },
    {
        "link": "https://www.seminovosmovida.com.br/veiculo/detalhe/SUV/Volkswagen/T-Cross/1004412",
        "title": "Volkswagen T-Cross",
        "version": "200 Tsi 1.0 Flex 12v 5p Aut.",
        "details": "2023/2024 • 56.829 KM • São José dos Campos, SP",
        "old_price": null,
        "new_price": "R$ 112.500",
        "parcela": "Entrada + parcelas a partir de R$ 1.666*"
    },
    {
        "link": "https://www.seminovosmovida.com.br/veiculo/detalhe/Sedan/Hyundai/Hb20S/1270355",
        "title": "Hyundai Hb20S",
        "version": "Limited 1.0 Tb Flex 12v Aut.",
        "details": "2025/2026 • 27.000 KM • Bauru, SP",
        "old_price": null,
        "new_price": "R$ 112.500",
        "parcela": "Entrada + parcelas a partir de R$ 1.666*"
    },
    {
        "link": "https://www.seminovosmovida.com.br/veiculo/detalhe/SUV/Nissan/Kicks/1262174",
        "title": "Nissan Kicks",
        "version": "Play Active Plus 1.6 16v Flex Aut.",
        "details": "2025/2025 • 29.560 KM • Uberlândia, MG",
        "old_price": null,
        "new_price": "R$ 112.500",
        "parcela": "Entrada + parcelas a partir de R$ 1.666*"
    },
    {
        "link": "https://www.seminovosmovida.com.br/veiculo/detalhe/SUV/Volkswagen/T-Cross/1005403",
        "title": "Volkswagen T-Cross",
        "version": "200 Tsi 1.0 Flex 12v 5p Aut.",
        "details": "2023/2024 • 58.897 KM • São Paulo Vila Carrão, SP",
        "old_price": null,
        "new_price": "R$ 112.500",
        "parcela": "Entrada + parcelas a partir de R$ 1.666*"
    },
    {
        "link": "https://www.seminovosmovida.com.br/veiculo/detalhe/Sedan/Hyundai/Hb20S/1270020",
        "title": "Hyundai Hb20S",
        "version": "Limited 1.0 Tb Flex 12v Aut.",
        "details": "2025/2026 • 29.569 KM • São Paulo Vila Ema, SP",
        "old_price": null,
        "new_price": "R$ 112.500",
        "parcela": "Entrada + parcelas a partir de R$ 1.666*"
    },
    {
        "link": "https://www.seminovosmovida.com.br/veiculo/detalhe/Sedan/Hyundai/Hb20S/1271266",
        "title": "Hyundai Hb20S",
        "version": "Limited 1.0 Tb Flex 12v Aut.",
        "details": "2025/2026 • 26.644 KM • São Paulo Santana, SP",
        "old_price": null,
        "new_price": "R$ 112.500",
        "parcela": "Entrada + parcelas a partir de R$ 1.666*"
    },
    {
        "link": "https://www.seminovosmovida.com.br/veiculo/detalhe/Sedan/Hyundai/Hb20S/1269519",
        "title": "Hyundai Hb20S",
        "version": "Limited 1.0 Tb Flex 12v Aut.",
        "details": "2025/2026 • 29.525 KM • São Paulo São Miguel, SP",
        "old_price": null,
        "new_price": "R$ 112.500",
        "parcela": "Entrada + parcelas a partir de R$ 1.666*"
    },
    {
        "link": "https://www.seminovosmovida.com.br/veiculo/detalhe/SUV/Volkswagen/T-Cross/1004408",
        "title": "Volkswagen T-Cross",
        "version": "200 Tsi 1.0 Flex 12v 5p Aut.",
        "details": "2023/2024 • 57.290 KM • Guarulhos Timoteo Penteado, SP",
        "old_price": null,
        "new_price": "R$ 112.500",
        "parcela": "Entrada + parcelas a partir de R$ 1.666*"
    },
    {
        "link": "https://www.seminovosmovida.com.br/veiculo/detalhe/Sedan/Hyundai/Hb20S/1269888",
        "title": "Hyundai Hb20S",
        "version": "Limited 1.0 Tb Flex 12v Aut.",
        "details": "2025/2026 • 26.556 KM • São Paulo São Miguel, SP",
        "old_price": null,
        "new_price": "R$ 112.500",
        "parcela": "Entrada + parcelas a partir de R$ 1.666*"
    },
    {
        "link": "https://www.seminovosmovida.com.br/veiculo/detalhe/Sedan/Hyundai/Hb20S/1270157",
        "title": "Hyundai Hb20S",
        "version": "Limited 1.0 Tb Flex 12v Aut.",
        "details": "2025/2026 • 26.404 KM • São Paulo São Miguel, SP",
        "old_price": null,
        "new_price": "R$ 112.500",
        "parcela": "Entrada + parcelas a partir de R$ 1.666*"
    },
    {
        "link": "https://www.seminovosmovida.com.br/veiculo/detalhe/Sedan/Hyundai/Hb20S/1270084",
        "title": "Hyundai Hb20S",
        "version": "Limited 1.0 Tb Flex 12v Aut.",
        "details": "2025/2026 • 28.434 KM • São Paulo Vila Ema, SP",
        "old_price": null,
        "new_price": "R$ 112.500",
        "parcela": "Entrada + parcelas a partir de R$ 1.666*"
    },
    {
        "link": "https://www.seminovosmovida.com.br/veiculo/detalhe/Sedan/Hyundai/Hb20S/1267548",
        "title": "Hyundai Hb20S",
        "version": "Limited 1.0 Tb Flex 12v Aut.",
        "details": "2025/2026 • 28.280 KM • São Paulo Eliseu de Almeida, SP",
        "old_price": null,
        "new_price": "R$ 112.500",
        "parcela": "Entrada + parcelas a partir de R$ 1.666*"
    },
    {
        "link": "https://www.seminovosmovida.com.br/veiculo/detalhe/Sedan/Hyundai/Hb20S/1270473",
        "title": "Hyundai Hb20S",
        "version": "Limited 1.0 Tb Flex 12v Aut.",
        "details": "2025/2026 • 26.089 KM • São Paulo Nações Unidas, SP",
        "old_price": null,
        "new_price": "R$ 112.500",
        "parcela": "Entrada + parcelas a partir de R$ 1.666*"
    },
    {
        "link": "https://www.seminovosmovida.com.br/veiculo/detalhe/SUV/Jeep/Renegade/981184",
        "title": "Jeep Renegade",
        "version": "Long. T270 1.3 Tb 4x2 Flex Aut.",
        "details": "2023/2024 • 54.717 KM • Auto Shopping Fortaleza, CE",
        "old_price": null,
        "new_price": "R$ 112.600",
        "parcela": "Entrada + parcelas a partir de R$ 1.667*"
    },
    {
        "link": "https://www.seminovosmovida.com.br/veiculo/detalhe/Sedan/Volkswagen/Virtus/1167822",
        "title": "Volkswagen Virtus",
        "version": "Comfort. 200 Tsi 1.0 Flex 12v Aut",
        "details": "2024/2025 • 63.292 KM • Salvador Paralela, BA",
        "old_price": null,
        "new_price": "R$ 112.600",
        "parcela": "Entrada + parcelas a partir de R$ 1.667*"
    },
    {
        "link": "https://www.seminovosmovida.com.br/veiculo/detalhe/SUV/Chevrolet/Tracker/1247466",
        "title": "Chevrolet Tracker",
        "version": "Lt 1.0 Turbo 12v Flex Aut.",
        "details": "2025/2025 • 29.476 KM • Goiânia Mutirão, GO",
        "old_price": null,
        "new_price": "R$ 112.600",
        "parcela": "Entrada + parcelas a partir de R$ 1.667*"
    },
    {
        "link": "https://www.seminovosmovida.com.br/veiculo/detalhe/Pickup/Fiat/Strada/1198313",
        "title": "Fiat Strada",
        "version": "Freedom 1.3 Flex 8v Cd",
        "details": "2024/2025 • 38.669 KM • Teresina, PI",
        "old_price": null,
        "new_price": "R$ 112.800",
        "parcela": "Entrada + parcelas a partir de R$ 1.670*"
    },
    {
        "link": "https://www.seminovosmovida.com.br/veiculo/detalhe/SUV/Nissan/Kicks/989362",
        "title": "Nissan Kicks",
        "version": "Sense 1.6 16v Flex Aut.",
        "details": "2023/2024 • 23.992 KM • Niterói, RJ",
        "old_price": null,
        "new_price": "R$ 112.800",
        "parcela": "Entrada + parcelas a partir de R$ 1.670*"
    },
    {
        "link": "https://www.seminovosmovida.com.br/veiculo/detalhe/SUV/Volkswagen/T-Cross/1124648",
        "title": "Volkswagen T-Cross",
        "version": "200 Tsi 1.0 Flex 12v 5p Aut.",
        "details": "2024/2024 • 68.056 KM • Recife Caxangá, PE",
        "old_price": null,
        "new_price": "R$ 112.900",
        "parcela": "Entrada + parcelas a partir de R$ 1.672*"
    },
    {
        "link": "https://www.seminovosmovida.com.br/veiculo/detalhe/SUV/Volkswagen/T-Cross/1126466",
        "title": "Volkswagen T-Cross",
        "version": "200 Tsi 1.0 Flex 12v 5p Aut.",
        "details": "2024/2024 • 45.181 KM • Recife Caxangá, PE",
        "old_price": null,
        "new_price": "R$ 112.900",
        "parcela": "Entrada + parcelas a partir de R$ 1.672*"
    },
    {
        "link": "https://www.seminovosmovida.com.br/veiculo/detalhe/SUV/Volkswagen/T-Cross/1127287",
        "title": "Volkswagen T-Cross",
        "version": "200 Tsi 1.0 Flex 12v 5p Aut.",
        "details": "2024/2024 • 63.600 KM • Recife Imbiribeira, PE",
        "old_price": null,
        "new_price": "R$ 112.900",
        "parcela": "Entrada + parcelas a partir de R$ 1.672*"
    },
    {
        "link": "https://www.seminovosmovida.com.br/veiculo/detalhe/SUV/Volkswagen/T-Cross/1125456",
        "title": "Volkswagen T-Cross",
        "version": "200 Tsi 1.0 Flex 12v 5p Aut.",
        "details": "2024/2024 • 45.607 KM • Auto Shopping Fortaleza, CE",
        "old_price": null,
        "new_price": "R$ 112.900",
        "parcela": "Entrada + parcelas a partir de R$ 1.672*"
    },
    {
        "link": "https://www.seminovosmovida.com.br/veiculo/detalhe/SUV/Volkswagen/T-Cross/1125456",
        "title": "Volkswagen T-Cross",
        "version": "200 Tsi 1.0 Flex 12v 5p Aut.",
        "details": "2024/2024 • 45.607 KM • Auto Shopping Fortaleza, CE",
        "old_price": null,
        "new_price": "R$ 112.900",
        "parcela": "Entrada + parcelas a partir de R$ 1.672*"
    },
    {
        "link": "https://www.seminovosmovida.com.br/veiculo/detalhe/SUV/Volkswagen/T-Cross/1125777",
        "title": "Volkswagen T-Cross",
        "version": "200 Tsi 1.0 Flex 12v 5p Aut.",
        "details": "2024/2024 • 35.887 KM • Jundiaí, SP",
        "old_price": null,
        "new_price": "R$ 112.900",
        "parcela": "Entrada + parcelas a partir de R$ 1.672*"
    },
    {
        "link": "https://www.seminovosmovida.com.br/veiculo/detalhe/SUV/Volkswagen/T-Cross/1126131",
        "title": "Volkswagen T-Cross",
        "version": "200 Tsi 1.0 Flex 12v 5p Aut.",
        "details": "2024/2024 • 36.000 KM • São Luís, MA",
        "old_price": null,
        "new_price": "R$ 112.900",
        "parcela": "Entrada + parcelas a partir de R$ 1.672*"
    },
    {
        "link": "https://www.seminovosmovida.com.br/veiculo/detalhe/Pickup/Fiat/Strada/1102522",
        "title": "Fiat Strada",
        "version": "Freedom 1.3 Flex 8v Cd",
        "details": "2024/2024 • 31.000 KM • Cuiabá, MT",
        "old_price": null,
        "new_price": "R$ 112.900",
        "parcela": "Entrada + parcelas a partir de R$ 1.672*"
    },
    {
        "link": "https://www.seminovosmovida.com.br/veiculo/detalhe/SUV/Volkswagen/T-Cross/1125927",
        "title": "Volkswagen T-Cross",
        "version": "200 Tsi 1.0 Flex 12v 5p Aut.",
        "details": "2024/2024 • 30.513 KM • São Paulo Nações Unidas, SP",
        "old_price": null,
        "new_price": "R$ 112.900",
        "parcela": "Entrada + parcelas a partir de R$ 1.672*"
    },
    {
        "link": "https://www.seminovosmovida.com.br/veiculo/detalhe/SUV/Volkswagen/T-Cross/1037392",
        "title": "Volkswagen T-Cross",
        "version": "200 Tsi 1.0 Flex 12v 5p Aut.",
        "details": "2023/2024 • 21.071 KM • Juiz de Fora, MG",
        "old_price": null,
        "new_price": "R$ 112.900",
        "parcela": "Entrada + parcelas a partir de R$ 1.672*"
    },
    {
        "link": "https://www.seminovosmovida.com.br/veiculo/detalhe/SUV/Nissan/Kicks/978760",
        "title": "Nissan Kicks",
        "version": "Sense 1.6 16v Flex Aut.",
        "details": "2023/2024 • 36.701 KM • Niterói, RJ",
        "old_price": null,
        "new_price": "R$ 112.900",
        "parcela": "Entrada + parcelas a partir de R$ 1.672*"
    },
    {
        "link": "https://www.seminovosmovida.com.br/veiculo/detalhe/SUV/Chevrolet/Tracker/1184862",
        "title": "Chevrolet Tracker",
        "version": "Lt 1.0 Turbo 12v Flex Aut.",
        "details": "2024/2025 • 32.038 KM • Mogi das Cruzes, SP",
        "old_price": null,
        "new_price": "R$ 113.100",
        "parcela": "Entrada + parcelas a partir de R$ 1.675*"
    },
    {
        "link": "https://www.seminovosmovida.com.br/veiculo/detalhe/SUV/Volkswagen/T-Cross/1125485",
        "title": "Volkswagen T-Cross",
        "version": "200 Tsi 1.0 Flex 12v 5p Aut.",
        "details": "2024/2024 • 37.513 KM • Lauro de Freitas, BA",
        "old_price": null,
        "new_price": "R$ 113.100",
        "parcela": "Entrada + parcelas a partir de R$ 1.675*"
    },
    {
        "link": "https://www.seminovosmovida.com.br/veiculo/detalhe/SUV/Chevrolet/Tracker/1146278",
        "title": "Chevrolet Tracker",
        "version": "Lt 1.0 Turbo 12v Flex Aut.",
        "details": "2024/2025 • 37.776 KM • João Pessoa Brisamar, PB",
        "old_price": null,
        "new_price": "R$ 113.100",
        "parcela": "Entrada + parcelas a partir de R$ 1.675*"
    },
    {
        "link": "https://www.seminovosmovida.com.br/veiculo/detalhe/SUV/Renault/Kardian/1255868",
        "title": "Renault Kardian",
        "version": "Prem. Ed Flex 1.0 Tb 12v 5p Aut.",
        "details": "2025/2025 • 18.303 KM • Belém Marco, PA",
        "old_price": null,
        "new_price": "R$ 113.100",
        "parcela": "Entrada + parcelas a partir de R$ 1.675*"
    },
    {
        "link": "https://www.seminovosmovida.com.br/veiculo/detalhe/SUV/Volkswagen/T-Cross/1125636",
        "title": "Volkswagen T-Cross",
        "version": "200 Tsi 1.0 Flex 12v 5p Aut.",
        "details": "2024/2024 • 35.142 KM • Lauro de Freitas, BA",
        "old_price": null,
        "new_price": "R$ 113.100",
        "parcela": "Entrada + parcelas a partir de R$ 1.675*"
    },
    {
        "link": "https://www.seminovosmovida.com.br/veiculo/detalhe/SUV/Jeep/Renegade/1078636",
        "title": "Jeep Renegade",
        "version": "Long. T270 1.3 Tb 4x2 Flex Aut.",
        "details": "2024/2024 • 61.436 KM • Brasília SIA, DF",
        "old_price": null,
        "new_price": "R$ 113.100",
        "parcela": "Entrada + parcelas a partir de R$ 1.675*"
    },
    {
        "link": "https://www.seminovosmovida.com.br/veiculo/detalhe/SUV/Jeep/Renegade/1063572",
        "title": "Jeep Renegade",
        "version": "Long. T270 1.3 Tb 4x2 Flex Aut.",
        "details": "2023/2024 • 63.521 KM • Porto Alegre Sarandi, RS",
        "old_price": null,
        "new_price": "R$ 113.100",
        "parcela": "Entrada + parcelas a partir de R$ 1.675*"
    },
    {
        "link": "https://www.seminovosmovida.com.br/veiculo/detalhe/SUV/Hyundai/Creta/1178218",
        "title": "Hyundai Creta",
        "version": "Action 1.6 16v Flex Aut.",
        "details": "2024/2025 • 26.807 KM • Auto Shopping Fortaleza, CE",
        "old_price": null,
        "new_price": "R$ 113.200",
        "parcela": "Entrada + parcelas a partir de R$ 1.676*"
    },
    {
        "link": "https://www.seminovosmovida.com.br/veiculo/detalhe/SUV/Jeep/Renegade/955579",
        "title": "Jeep Renegade",
        "version": "Long. T270 1.3 Tb 4x2 Flex Aut.",
        "details": "2023/2024 • 57.161 KM • Rio de Janeiro Recreio dos Bandeirantes, RJ",
        "old_price": null,
        "new_price": "R$ 113.200",
        "parcela": "Entrada + parcelas a partir de R$ 1.676*"
    },
    {
        "link": "https://www.seminovosmovida.com.br/veiculo/detalhe/Sedan/Volkswagen/Virtus/1044988",
        "title": "Volkswagen Virtus",
        "version": "Highline 200 Tsi 1.0 Flex 12v Aut",
        "details": "2023/2024 • 81.684 KM • Auto Shopping Arena Motors, SP",
        "old_price": null,
        "new_price": "R$ 113.200",
        "parcela": "Entrada + parcelas a partir de R$ 1.676*"
    },
    {
        "link": "https://www.seminovosmovida.com.br/veiculo/detalhe/SUV/Hyundai/Creta/1178335",
        "title": "Hyundai Creta",
        "version": "Action 1.6 16v Flex Aut.",
        "details": "2024/2025 • 23.832 KM • Natal, RN",
        "old_price": null,
        "new_price": "R$ 113.200",
        "parcela": "Entrada + parcelas a partir de R$ 1.676*"
    },
    {
        "link": "https://www.seminovosmovida.com.br/veiculo/detalhe/SUV/Hyundai/Creta/1170880",
        "title": "Hyundai Creta",
        "version": "Action 1.6 16v Flex Aut.",
        "details": "2024/2025 • 18.193 KM • Belém Senador, PA",
        "old_price": null,
        "new_price": "R$ 113.200",
        "parcela": "Entrada + parcelas a partir de R$ 1.676*"
    },
    {
        "link": "https://www.seminovosmovida.com.br/veiculo/detalhe/SUV/Hyundai/Creta/1160111",
        "title": "Hyundai Creta",
        "version": "Action 1.6 16v Flex Aut.",
        "details": "2024/2025 • 29.359 KM • Auto Shopping Portal, MG",
        "old_price": null,
        "new_price": "R$ 113.200",
        "parcela": "Entrada + parcelas a partir de R$ 1.676*"
    },
    {
        "link": "https://www.seminovosmovida.com.br/veiculo/detalhe/SUV/Hyundai/Creta/1149025",
        "title": "Hyundai Creta",
        "version": "Action 1.6 16v Flex Aut.",
        "details": "2024/2025 • 20.238 KM • Belo Horizonte Antonio Carlos, MG",
        "old_price": null,
        "new_price": "R$ 113.200",
        "parcela": "Entrada + parcelas a partir de R$ 1.676*"
    },
    {
        "link": "https://www.seminovosmovida.com.br/veiculo/detalhe/Hatch/Volkswagen/Polo/1154288",
        "title": "Volkswagen Polo",
        "version": "Highline Tsi 1.0 Flex 12v Aut.",
        "details": "2024/2025 • 28.260 KM • Osasco, SP",
        "old_price": null,
        "new_price": "R$ 113.300",
        "parcela": "Entrada + parcelas a partir de R$ 1.677*"
    },
    {
        "link": "https://www.seminovosmovida.com.br/veiculo/detalhe/SUV/Renault/Duster/1240381",
        "title": "Renault Duster",
        "version": "Intense Plus 1.6 16v Flex Aut.",
        "details": "2024/2025 • 28.415 KM • São Paulo Vila Guilherme, SP",
        "old_price": null,
        "new_price": "R$ 113.400",
        "parcela": "Entrada + parcelas a partir de R$ 1.679*"
    },
    {
        "link": "https://www.seminovosmovida.com.br/veiculo/detalhe/SUV/Renault/Duster/1240324",
        "title": "Renault Duster",
        "version": "Intense Plus 1.6 16v Flex Aut.",
        "details": "2024/2025 • 39.100 KM • Piracicaba, SP",
        "old_price": null,
        "new_price": "R$ 113.400",
        "parcela": "Entrada + parcelas a partir de R$ 1.679*"
    },
    {
        "link": "https://www.seminovosmovida.com.br/veiculo/detalhe/SUV/Renault/Duster/1240355",
        "title": "Renault Duster",
        "version": "Intense Plus 1.6 16v Flex Aut.",
        "details": "2024/2025 • 34.761 KM • São José do Rio Preto, SP",
        "old_price": null,
        "new_price": "R$ 113.400",
        "parcela": "Entrada + parcelas a partir de R$ 1.679*"
    },
    {
        "link": "https://www.seminovosmovida.com.br/veiculo/detalhe/SUV/Renault/Duster/1240596",
        "title": "Renault Duster",
        "version": "Intense Plus 1.6 16v Flex Aut.",
        "details": "2024/2025 • 25.856 KM • Auto Shopping Bandeirantes, SP",
        "old_price": null,
        "new_price": "R$ 113.400",
        "parcela": "Entrada + parcelas a partir de R$ 1.679*"
    },
    {
        "link": "https://www.seminovosmovida.com.br/veiculo/detalhe/SUV/Renault/Duster/1240524",
        "title": "Renault Duster",
        "version": "Intense Plus 1.6 16v Flex Aut.",
        "details": "2024/2025 • 39.230 KM • Limeira, SP",
        "old_price": null,
        "new_price": "R$ 113.400",
        "parcela": "Entrada + parcelas a partir de R$ 1.679*"
    },
    {
        "link": "https://www.seminovosmovida.com.br/veiculo/detalhe/SUV/Renault/Duster/1240473",
        "title": "Renault Duster",
        "version": "Intense Plus 1.6 16v Flex Aut.",
        "details": "2024/2025 • 39.500 KM • Santo André, SP",
        "old_price": null,
        "new_price": "R$ 113.400",
        "parcela": "Entrada + parcelas a partir de R$ 1.679*"
    },
    {
        "link": "https://www.seminovosmovida.com.br/veiculo/detalhe/SUV/Renault/Duster/1240469",
        "title": "Renault Duster",
        "version": "Intense Plus 1.6 16v Flex Aut.",
        "details": "2024/2025 • 30.646 KM • São Bernardo do Campo, SP",
        "old_price": null,
        "new_price": "R$ 113.400",
        "parcela": "Entrada + parcelas a partir de R$ 1.679*"
    },
    {
        "link": "https://www.seminovosmovida.com.br/veiculo/detalhe/SUV/Nissan/Kicks/980772",
        "title": "Nissan Kicks",
        "version": "Sense 1.6 16v Flex Aut.",
        "details": "2023/2024 • 28.011 KM • Recife Imbiribeira, PE",
        "old_price": null,
        "new_price": "R$ 113.400",
        "parcela": "Entrada + parcelas a partir de R$ 1.679*"
    },
    {
        "link": "https://www.seminovosmovida.com.br/veiculo/detalhe/SUV/Renault/Duster/1236337",
        "title": "Renault Duster",
        "version": "Intense Plus 1.6 16v Flex Aut.",
        "details": "2024/2025 • 28.688 KM • Campinas Orosimbo, SP",
        "old_price": null,
        "new_price": "R$ 113.400",
        "parcela": "Entrada + parcelas a partir de R$ 1.679*"
    },
    {
        "link": "https://www.seminovosmovida.com.br/veiculo/detalhe/SUV/Renault/Duster/1240617",
        "title": "Renault Duster",
        "version": "Intense Plus 1.6 16v Flex Aut.",
        "details": "2024/2025 • 29.161 KM • Auto Shopping Autonomistas, SP",
        "old_price": null,
        "new_price": "R$ 113.400",
        "parcela": "Entrada + parcelas a partir de R$ 1.679*"
    },
    {
        "link": "https://www.seminovosmovida.com.br/veiculo/detalhe/Pickup/Fiat/Strada/1135636",
        "title": "Fiat Strada",
        "version": "Freedom 1.3 Flex 8v Cd",
        "details": "2024/2025 • 49.769 KM • Auto Shopping Fortaleza, CE",
        "old_price": null,
        "new_price": "R$ 113.400",
        "parcela": "Entrada + parcelas a partir de R$ 1.679*"
    },
    {
        "link": "https://www.seminovosmovida.com.br/veiculo/detalhe/SUV/Jeep/Renegade/970034",
        "title": "Jeep Renegade",
        "version": "Long. T270 1.3 Tb 4x2 Flex Aut.",
        "details": "2023/2024 • 50.959 KM • Contagem Babita Camargo, MG",
        "old_price": null,
        "new_price": "R$ 113.500",
        "parcela": "Entrada + parcelas a partir de R$ 1.680*"
    },
    {
        "link": "https://www.seminovosmovida.com.br/veiculo/detalhe/SUV/Volkswagen/T-Cross/1124572",
        "title": "Volkswagen T-Cross",
        "version": "200 Tsi 1.0 Flex 12v 5p Aut.",
        "details": "2024/2024 • 52.684 KM • Auto Shopping Fortaleza, CE",
        "old_price": null,
        "new_price": "R$ 113.600",
        "parcela": "Entrada + parcelas a partir de R$ 1.682*"
    },
    {
        "link": "https://www.seminovosmovida.com.br/veiculo/detalhe/SUV/Volkswagen/T-Cross/1006651",
        "title": "Volkswagen T-Cross",
        "version": "200 Tsi 1.0 Flex 12v 5p Aut.",
        "details": "2023/2024 • 59.898 KM • Auto Shopping Mundo Car, SC",
        "old_price": null,
        "new_price": "R$ 113.600",
        "parcela": "Entrada + parcelas a partir de R$ 1.682*"
    },
    {
        "link": "https://www.seminovosmovida.com.br/veiculo/detalhe/SUV/Volkswagen/T-Cross/1016602",
        "title": "Volkswagen T-Cross",
        "version": "200 Tsi 1.0 Flex 12v 5p Aut.",
        "details": "2023/2024 • 55.140 KM • Blumenau, SC",
        "old_price": null,
        "new_price": "R$ 113.600",
        "parcela": "Entrada + parcelas a partir de R$ 1.682*"
    },
    {
        "link": "https://www.seminovosmovida.com.br/veiculo/detalhe/SUV/Volkswagen/T-Cross/1114807",
        "title": "Volkswagen T-Cross",
        "version": "200 Tsi 1.0 Flex 12v 5p Aut.",
        "details": "2024/2024 • 55.744 KM • Lauro de Freitas, BA",
        "old_price": null,
        "new_price": "R$ 113.800",
        "parcela": "Entrada + parcelas a partir de R$ 1.685*"
    },
    {
        "link": "https://www.seminovosmovida.com.br/veiculo/detalhe/SUV/Renault/Duster/1240508",
        "title": "Renault Duster",
        "version": "Intense Plus 1.6 16v Flex Aut.",
        "details": "2024/2025 • 36.816 KM • Blumenau, SC",
        "old_price": null,
        "new_price": "R$ 113.800",
        "parcela": "Entrada + parcelas a partir de R$ 1.685*"
    },
    {
        "link": "https://www.seminovosmovida.com.br/veiculo/detalhe/SUV/Renault/Duster/1240459",
        "title": "Renault Duster",
        "version": "Intense Plus 1.6 16v Flex Aut.",
        "details": "2024/2025 • 34.052 KM • Itajaí, SC",
        "old_price": null,
        "new_price": "R$ 113.800",
        "parcela": "Entrada + parcelas a partir de R$ 1.685*"
    },
    {
        "link": "https://www.seminovosmovida.com.br/veiculo/detalhe/SUV/Renault/Duster/1240425",
        "title": "Renault Duster",
        "version": "Intense Plus 1.6 16v Flex Aut.",
        "details": "2024/2025 • 38.568 KM • Fortaleza, CE",
        "old_price": null,
        "new_price": "R$ 113.800",
        "parcela": "Entrada + parcelas a partir de R$ 1.685*"
    },
    {
        "link": "https://www.seminovosmovida.com.br/veiculo/detalhe/Pickup/Fiat/Strada/1226434",
        "title": "Fiat Strada",
        "version": "Freedom 1.3 Flex 8v Cd",
        "details": "2024/2025 • 32.101 KM • Aparecida de Goiânia, GO",
        "old_price": null,
        "new_price": "R$ 113.800",
        "parcela": "Entrada + parcelas a partir de R$ 1.685*"
    },
    {
        "link": "https://www.seminovosmovida.com.br/veiculo/detalhe/SUV/Renault/Duster/1240361",
        "title": "Renault Duster",
        "version": "Intense Plus 1.6 16v Flex Aut.",
        "details": "2024/2025 • 35.158 KM • Rio de Janeiro Barra da Tijuca, RJ",
        "old_price": null,
        "new_price": "R$ 113.800",
        "parcela": "Entrada + parcelas a partir de R$ 1.685*"
    },
    {
        "link": "https://www.seminovosmovida.com.br/veiculo/detalhe/SUV/Fiat/Fastback/1153666",
        "title": "Fiat Fastback",
        "version": "Audace 1.0 200 T. Flex Aut",
        "details": "2024/2025 • 59.984 KM • João Pessoa Brisamar, PB",
        "old_price": null,
        "new_price": "R$ 113.800",
        "parcela": "Entrada + parcelas a partir de R$ 1.685*"
    },
    {
        "link": "https://www.seminovosmovida.com.br/veiculo/detalhe/SUV/Renault/Duster/1240390",
        "title": "Renault Duster",
        "version": "Intense Plus 1.6 16v Flex Aut.",
        "details": "2024/2025 • 32.622 KM • Fortaleza Av. Santos Dumont, CE",
        "old_price": null,
        "new_price": "R$ 113.800",
        "parcela": "Entrada + parcelas a partir de R$ 1.685*"
    },
    {
        "link": "https://www.seminovosmovida.com.br/veiculo/detalhe/SUV/Renault/Duster/1240407",
        "title": "Renault Duster",
        "version": "Intense Plus 1.6 16v Flex Aut.",
        "details": "2024/2025 • 33.437 KM • Rio de Janeiro Vila Valqueire, RJ",
        "old_price": null,
        "new_price": "R$ 113.800",
        "parcela": "Entrada + parcelas a partir de R$ 1.685*"
    },
    {
        "link": "https://www.seminovosmovida.com.br/veiculo/detalhe/SUV/Renault/Duster/1240457",
        "title": "Renault Duster",
        "version": "Intense Plus 1.6 16v Flex Aut.",
        "details": "2024/2025 • 39.732 KM • Rio de Janeiro Vila Valqueire, RJ",
        "old_price": null,
        "new_price": "R$ 113.800",
        "parcela": "Entrada + parcelas a partir de R$ 1.685*"
    },
    {
        "link": "https://www.seminovosmovida.com.br/veiculo/detalhe/SUV/Volkswagen/T-Cross/997239",
        "title": "Volkswagen T-Cross",
        "version": "200 Tsi 1.0 Flex 12v 5p Aut.",
        "details": "2023/2024 • 45.280 KM • Nova Iguaçu, RJ",
        "old_price": null,
        "new_price": "R$ 113.900",
        "parcela": "Entrada + parcelas a partir de R$ 1.686*"
    },
    {
        "link": "https://www.seminovosmovida.com.br/veiculo/detalhe/SUV/Volkswagen/T-Cross/1005838",
        "title": "Volkswagen T-Cross",
        "version": "200 Tsi 1.0 Flex 12v 5p Aut.",
        "details": "2023/2024 • 46.098 KM • Rio de Janeiro Campo Grande, RJ",
        "old_price": null,
        "new_price": "R$ 113.900",
        "parcela": "Entrada + parcelas a partir de R$ 1.686*"
    },
    {
        "link": "https://www.seminovosmovida.com.br/veiculo/detalhe/SUV/Volkswagen/T-Cross/1016563",
        "title": "Volkswagen T-Cross",
        "version": "200 Tsi 1.0 Flex 12v 5p Aut.",
        "details": "2023/2024 • 44.999 KM • Auto Shopping Shopping Car, RJ",
        "old_price": null,
        "new_price": "R$ 113.900",
        "parcela": "Entrada + parcelas a partir de R$ 1.686*"
    },
    {
        "link": "https://www.seminovosmovida.com.br/veiculo/detalhe/SUV/Nissan/Kicks/1072276",
        "title": "Nissan Kicks",
        "version": "Sense 1.6 16v Flex Aut.",
        "details": "2024/2024 • 39.078 KM • Piracicaba, SP",
        "old_price": null,
        "new_price": "R$ 114.000",
        "parcela": "Entrada + parcelas a partir de R$ 1.688*"
    },
    {
        "link": "https://www.seminovosmovida.com.br/veiculo/detalhe/SUV/Nissan/Kicks/987348",
        "title": "Nissan Kicks",
        "version": "Sense 1.6 16v Flex Aut.",
        "details": "2023/2024 • 36.902 KM • Santo André, SP",
        "old_price": null,
        "new_price": "R$ 114.000",
        "parcela": "Entrada + parcelas a partir de R$ 1.688*"
    },
    {
        "link": "https://www.seminovosmovida.com.br/veiculo/detalhe/SUV/Nissan/Kicks/1114162",
        "title": "Nissan Kicks",
        "version": "Sense 1.6 16v Flex Aut.",
        "details": "2024/2024 • 24.966 KM • São Paulo Aricanduva, SP",
        "old_price": null,
        "new_price": "R$ 114.000",
        "parcela": "Entrada + parcelas a partir de R$ 1.688*"
    },
    {
        "link": "https://www.seminovosmovida.com.br/veiculo/detalhe/SUV/Volkswagen/T-Cross/1039072",
        "title": "Volkswagen T-Cross",
        "version": "200 Tsi 1.0 Flex 12v 5p Aut.",
        "details": "2023/2024 • 27.244 KM • Santos, SP",
        "old_price": null,
        "new_price": "R$ 114.000",
        "parcela": "Entrada + parcelas a partir de R$ 1.688*"
    },
    {
        "link": "https://www.seminovosmovida.com.br/veiculo/detalhe/SUV/Nissan/Kicks/1154843",
        "title": "Nissan Kicks",
        "version": "Sense 1.6 16v Flex Aut.",
        "details": "2024/2024 • 25.223 KM • Rio de Janeiro Av. das Américas, RJ",
        "old_price": null,
        "new_price": "R$ 114.000",
        "parcela": "Consulte aqui o valor por assinatura"
    },
    {
        "link": "https://www.seminovosmovida.com.br/veiculo/detalhe/SUV/Volkswagen/T-Cross/1083075",
        "title": "Volkswagen T-Cross",
        "version": "200 Tsi 1.0 Flex 12v 5p Aut.",
        "details": "2024/2024 • 31.658 KM • Curitiba Mario Tourinho, PR",
        "old_price": null,
        "new_price": "R$ 114.000",
        "parcela": "Entrada + parcelas a partir de R$ 1.688*"
    },
    {
        "link": "https://www.seminovosmovida.com.br/veiculo/detalhe/SUV/Volkswagen/T-Cross/1114745",
        "title": "Volkswagen T-Cross",
        "version": "200 Tsi 1.0 Flex 12v 5p Aut.",
        "details": "2024/2024 • 45.119 KM • São Paulo Vila Ema, SP",
        "old_price": null,
        "new_price": "R$ 114.200",
        "parcela": "Entrada + parcelas a partir de R$ 1.691*"
    },
    {
        "link": "https://www.seminovosmovida.com.br/veiculo/detalhe/SUV/Volkswagen/T-Cross/1004457",
        "title": "Volkswagen T-Cross",
        "version": "200 Tsi 1.0 Flex 12v 5p Aut.",
        "details": "2023/2024 • 48.223 KM • São Paulo Nações Unidas, SP",
        "old_price": null,
        "new_price": "R$ 114.200",
        "parcela": "Entrada + parcelas a partir de R$ 1.691*"
    },
    {
        "link": "https://www.seminovosmovida.com.br/veiculo/detalhe/SUV/Volkswagen/T-Cross/1004369",
        "title": "Volkswagen T-Cross",
        "version": "200 Tsi 1.0 Flex 12v 5p Aut.",
        "details": "2023/2024 • 45.932 KM • São Paulo Vila Carrão, SP",
        "old_price": null,
        "new_price": "R$ 114.200",
        "parcela": "Entrada + parcelas a partir de R$ 1.691*"
    },
    {
        "link": "https://www.seminovosmovida.com.br/veiculo/detalhe/SUV/Volkswagen/T-Cross/1005367",
        "title": "Volkswagen T-Cross",
        "version": "200 Tsi 1.0 Flex 12v 5p Aut.",
        "details": "2023/2024 • 41.514 KM • Sorocaba Dom Aguirre, SP",
        "old_price": null,
        "new_price": "R$ 114.200",
        "parcela": "Entrada + parcelas a partir de R$ 1.691*"
    }
]