[
    {
        "link": "https://www.seminovosmovida.com.br/veiculo/detalhe/Sedan/Renault/Logan/1193497",
        "title": "Renault Logan",
        "version": "Zen Flex 1.0 12v 4p Mec.",
        "details": "2024/2025 • 19.356 KM • Fortaleza, CE",
        "old_price": null,
        "new_price": "R$ 75.300",
        "parcela": "Entrada + parcelas a partir de R$ 1.115*"
    },
    {
        "link": "https://www.seminovosmovida.com.br/veiculo/detalhe/Hatch/Volkswagen/Polo/1104717",
        "title": "Volkswagen Polo",
        "version": "Track 1.0 Flex 12v 5p",
        "details": "2024/2024 • 31.511 KM • Rio de Janeiro Campo Grande, RJ",
        "old_price": null,
        "new_price": "R$ 75.300",
        "parcela": "Entrada + parcelas a partir de R$ 1.115*"
    },
    {
        "link": "https://www.seminovosmovida.com.br/veiculo/detalhe/Sedan/Renault/Logan/1193821",
        "title": "Renault Logan",
        "version": "Zen Flex 1.0 12v 4p Mec.",
        "details": "2024/2025 • 38.660 KM • Salvador Paralela, BA",
        "old_price": null,
        "new_price": "R$ 75.300",
        "parcela": "Entrada + parcelas a partir de R$ 1.115*"
    },
    {
        "link": "https://www.seminovosmovida.com.br/veiculo/detalhe/Sedan/Renault/Logan/1164814",
        "title": "Renault Logan",
        "version": "Zen Flex 1.0 12v 4p Mec.",
        "details": "2024/2025 • 39.126 KM • Natal, RN",
        "old_price": null,
        "new_price": "R$ 75.300",
        "parcela": "Entrada + parcelas a partir de R$ 1.115*"
    },
    {
        "link": "https://www.seminovosmovida.com.br/veiculo/detalhe/Sedan/Renault/Logan/1180685",
        "title": "Renault Logan",
        "version": "Zen Flex 1.0 12v 4p Mec.",
        "details": "2024/2025 • 32.286 KM • Belém Marco, PA",
        "old_price": null,
        "new_price": "R$ 75.300",
        "parcela": "Entrada + parcelas a partir de R$ 1.115*"
    },
    {
        "link": "https://www.seminovosmovida.com.br/veiculo/detalhe/Sedan/Hyundai/Hb20S/623040",
        "title": "Hyundai Hb20S",
        "version": "Evolution 1.0 Tb Flex 12v Aut.",
        "details": "2020/2020 • 56.112 KM • Contagem Babita Camargo, MG",
        "old_price": null,
        "new_price": "R$ 75.300",
        "parcela": "Entrada + parcelas a partir de R$ 1.115*"
    },
    {
        "link": "https://www.seminovosmovida.com.br/veiculo/detalhe/Hatch/Volkswagen/Polo/1097711",
        "title": "Volkswagen Polo",
        "version": "Track 1.0 Flex 12v 5p",
        "details": "2024/2024 • 62.763 KM • Lauro de Freitas, BA",
        "old_price": null,
        "new_price": "R$ 75.300",
        "parcela": "Entrada + parcelas a partir de R$ 1.115*"
    },
    {
        "link": "https://www.seminovosmovida.com.br/veiculo/detalhe/Hatch/Volkswagen/Polo/1103841",
        "title": "Volkswagen Polo",
        "version": "Track 1.0 Flex 12v 5p",
        "details": "2024/2024 • 49.576 KM • Feira de Santana, BA",
        "old_price": null,
        "new_price": "R$ 75.300",
        "parcela": "Entrada + parcelas a partir de R$ 1.115*"
    },
    {
        "link": "https://www.seminovosmovida.com.br/veiculo/detalhe/Sedan/Renault/Logan/1180691",
        "title": "Renault Logan",
        "version": "Zen Flex 1.0 12v 4p Mec.",
        "details": "2024/2025 • 39.792 KM • Várzea Grande, MT",
        "old_price": null,
        "new_price": "R$ 75.300",
        "parcela": "Entrada + parcelas a partir de R$ 1.115*"
    },
    {
        "link": "https://www.seminovosmovida.com.br/veiculo/detalhe/Sedan/Renault/Logan/1193909",
        "title": "Renault Logan",
        "version": "Zen Flex 1.0 12v 4p Mec.",
        "details": "2024/2025 • 37.019 KM • Porto Alegre Ipiranga, RS",
        "old_price": null,
        "new_price": "R$ 75.300",
        "parcela": "Entrada + parcelas a partir de R$ 1.115*"
    },
    {
        "link": "https://www.seminovosmovida.com.br/veiculo/detalhe/Sedan/Renault/Logan/1193881",
        "title": "Renault Logan",
        "version": "Zen Flex 1.0 12v 4p Mec.",
        "details": "2024/2025 • 33.050 KM • Porto Alegre Ipiranga, RS",
        "old_price": null,
        "new_price": "R$ 75.300",
        "parcela": "Entrada + parcelas a partir de R$ 1.115*"
    },
    {
        "link": "https://www.seminovosmovida.com.br/veiculo/detalhe/Sedan/Renault/Logan/1180472",
        "title": "Renault Logan",
        "version": "Zen Flex 1.0 12v 4p Mec.",
        "details": "2024/2025 • 35.923 KM • Goiânia Mutirão, GO",
        "old_price": null,
        "new_price": "R$ 75.300",
        "parcela": "Entrada + parcelas a partir de R$ 1.115*"
    },
    {
        "link": "https://www.seminovosmovida.com.br/veiculo/detalhe/Sedan/Renault/Logan/1193397",
        "title": "Renault Logan",
        "version": "Zen Flex 1.0 12v 4p Mec.",
        "details": "2024/2025 • 31.421 KM • São Luís, MA",
        "old_price": null,
        "new_price": "R$ 75.300",
        "parcela": "Entrada + parcelas a partir de R$ 1.115*"
    },
    {
        "link": "https://www.seminovosmovida.com.br/veiculo/detalhe/Sedan/Renault/Logan/1193717",
        "title": "Renault Logan",
        "version": "Zen Flex 1.0 12v 4p Mec.",
        "details": "2024/2025 • 31.343 KM • Belém Marco, PA",
        "old_price": null,
        "new_price": "R$ 75.300",
        "parcela": "Entrada + parcelas a partir de R$ 1.115*"
    },
    {
        "link": "https://www.seminovosmovida.com.br/veiculo/detalhe/Sedan/Renault/Logan/1194097",
        "title": "Renault Logan",
        "version": "Zen Flex 1.0 12v 4p Mec.",
        "details": "2024/2025 • 31.350 KM • Natal, RN",
        "old_price": null,
        "new_price": "R$ 75.300",
        "parcela": "Entrada + parcelas a partir de R$ 1.115*"
    },
    {
        "link": "https://www.seminovosmovida.com.br/veiculo/detalhe/Hatch/Volkswagen/Polo/1081785",
        "title": "Volkswagen Polo",
        "version": "Track 1.0 Flex 12v 5p",
        "details": "2024/2024 • 36.085 KM • Rio de Janeiro Duque de Caxias, RJ",
        "old_price": null,
        "new_price": "R$ 75.300",
        "parcela": "Entrada + parcelas a partir de R$ 1.115*"
    },
    {
        "link": "https://www.seminovosmovida.com.br/veiculo/detalhe/Sedan/Renault/Logan/1199576",
        "title": "Renault Logan",
        "version": "Zen Flex 1.0 12v 4p Mec.",
        "details": "2024/2025 • 35.317 KM • Curitiba Mario Tourinho, PR",
        "old_price": null,
        "new_price": "R$ 75.300",
        "parcela": "Entrada + parcelas a partir de R$ 1.115*"
    },
    {
        "link": "https://www.seminovosmovida.com.br/veiculo/detalhe/Hatch/Volkswagen/Polo/1034693",
        "title": "Volkswagen Polo",
        "version": "Track 1.0 Flex 12v 5p",
        "details": "2023/2024 • 47.433 KM • São Bernardo Pereira Barreto, SP",
        "old_price": null,
        "new_price": "R$ 75.300",
        "parcela": "Entrada + parcelas a partir de R$ 1.115*"
    },
    {
        "link": "https://www.seminovosmovida.com.br/veiculo/detalhe/Sedan/Renault/Logan/1193737",
        "title": "Renault Logan",
        "version": "Zen Flex 1.0 12v 4p Mec.",
        "details": "2024/2025 • 32.075 KM • Maceió, AL",
        "old_price": null,
        "new_price": "R$ 75.300",
        "parcela": "Entrada + parcelas a partir de R$ 1.115*"
    },
    {
        "link": "https://www.seminovosmovida.com.br/veiculo/detalhe/Hatch/Volkswagen/Polo/1080974",
        "title": "Volkswagen Polo",
        "version": "Track 1.0 Flex 12v 5p",
        "details": "2024/2024 • 67.840 KM • Brasília SIA, DF",
        "old_price": null,
        "new_price": "R$ 75.300",
        "parcela": "Entrada + parcelas a partir de R$ 1.115*"
    },
    {
        "link": "https://www.seminovosmovida.com.br/veiculo/detalhe/Pickup/Volkswagen/Saveiro/1109776",
        "title": "Volkswagen Saveiro",
        "version": "Robust 1.6 Total Flex 16v",
        "details": "2024/2024 • 59.754 KM • Joinville, SC",
        "old_price": null,
        "new_price": "R$ 75.400",
        "parcela": "Entrada + parcelas a partir de R$ 1.116*"
    },
    {
        "link": "https://www.seminovosmovida.com.br/veiculo/detalhe/Hatch/Hyundai/Hb20/1239815",
        "title": "Hyundai Hb20",
        "version": "Sense Plus 1.0 Flex 12v Mec.",
        "details": "2024/2025 • 13.917 KM • Belém Senador, PA",
        "old_price": null,
        "new_price": "R$ 75.400",
        "parcela": "Entrada + parcelas a partir de R$ 1.116*"
    },
    {
        "link": "https://www.seminovosmovida.com.br/veiculo/detalhe/Pickup/Volkswagen/Saveiro/1082748",
        "title": "Volkswagen Saveiro",
        "version": "Robust 1.6 Total Flex 16v",
        "details": "2024/2024 • 59.633 KM • Serra, ES",
        "old_price": null,
        "new_price": "R$ 75.400",
        "parcela": "Entrada + parcelas a partir de R$ 1.116*"
    },
    {
        "link": "https://www.seminovosmovida.com.br/veiculo/detalhe/Pickup/Fiat/Strada/933064",
        "title": "Fiat Strada",
        "version": "Endurance 1.4 Flex 8v Cs Plus",
        "details": "2023/2023 • 78.359 KM • Auto Shopping Passeio das Águas, GO",
        "old_price": null,
        "new_price": "R$ 75.400",
        "parcela": "Entrada + parcelas a partir de R$ 1.116*"
    },
    {
        "link": "https://www.seminovosmovida.com.br/veiculo/detalhe/Pickup/Volkswagen/Saveiro/989846",
        "title": "Volkswagen Saveiro",
        "version": "Robust 1.6 Total Flex 16v",
        "details": "2023/2024 • 51.934 KM • Belo Horizonte Antonio Carlos, MG",
        "old_price": null,
        "new_price": "R$ 75.400",
        "parcela": "Entrada + parcelas a partir de R$ 1.116*"
    },
    {
        "link": "https://www.seminovosmovida.com.br/veiculo/detalhe/Hatch/Citroen/C3/1248662",
        "title": "Citroen C3",
        "version": "Feel 1.0 Flex 6v 5p Mec.",
        "details": "2025/2025 • 27.560 KM • Campinas Amoreiras, SP",
        "old_price": null,
        "new_price": "R$ 75.400",
        "parcela": "Entrada + parcelas a partir de R$ 1.116*"
    },
    {
        "link": "https://www.seminovosmovida.com.br/veiculo/detalhe/Pickup/Fiat/Strada/933066",
        "title": "Fiat Strada",
        "version": "Endurance 1.4 Flex 8v Cs Plus",
        "details": "2023/2023 • 79.181 KM • Auto Shopping Passeio das Águas, GO",
        "old_price": null,
        "new_price": "R$ 75.400",
        "parcela": "Entrada + parcelas a partir de R$ 1.116*"
    },
    {
        "link": "https://www.seminovosmovida.com.br/veiculo/detalhe/Hatch/Fiat/Argo/1157002",
        "title": "Fiat Argo",
        "version": "1.0 6v Flex",
        "details": "2024/2025 • 36.787 KM • Sorocaba Dom Aguirre, SP",
        "old_price": null,
        "new_price": "R$ 75.400",
        "parcela": "Entrada + parcelas a partir de R$ 1.116*"
    },
    {
        "link": "https://www.seminovosmovida.com.br/veiculo/detalhe/Pickup/Volkswagen/Saveiro/1106830",
        "title": "Volkswagen Saveiro",
        "version": "Robust 1.6 Total Flex 16v",
        "details": "2024/2024 • 45.501 KM • Auto Shopping Lauro de Freitas, BA",
        "old_price": null,
        "new_price": "R$ 75.400",
        "parcela": "Entrada + parcelas a partir de R$ 1.116*"
    },
    {
        "link": "https://www.seminovosmovida.com.br/veiculo/detalhe/Hatch/Citroen/C3/1243968",
        "title": "Citroen C3",
        "version": "Live Pack 1.0 Flex 6v 5p Mec.",
        "details": "2024/2025 • 16.406 KM • Maringá, PR",
        "old_price": null,
        "new_price": "R$ 75.400",
        "parcela": "Entrada + parcelas a partir de R$ 1.116*"
    },
    {
        "link": "https://www.seminovosmovida.com.br/veiculo/detalhe/SUV/Citroen/C4/782836",
        "title": "Citroen C4",
        "version": "Cactus Feel 1.6 16v Flex Aut.",
        "details": "2021/2022 • 107.484 KM • São Paulo Vila Guilherme, SP",
        "old_price": null,
        "new_price": "R$ 75.400",
        "parcela": "Entrada + parcelas a partir de R$ 1.116*"
    },
    {
        "link": "https://www.seminovosmovida.com.br/veiculo/detalhe/Hatch/Citroen/C3/1199113",
        "title": "Citroen C3",
        "version": "Live Pack 1.0 Flex 6v 5p Mec.",
        "details": "2024/2025 • 11.342 KM • Campo Grande, MS",
        "old_price": null,
        "new_price": "R$ 75.400",
        "parcela": "Entrada + parcelas a partir de R$ 1.116*"
    },
    {
        "link": "https://www.seminovosmovida.com.br/veiculo/detalhe/Hatch/Fiat/Argo/1212257",
        "title": "Fiat Argo",
        "version": "Drive 1.0 6v Flex",
        "details": "2024/2025 • 48.454 KM • Mogi das Cruzes, SP",
        "old_price": null,
        "new_price": "R$ 75.500",
        "parcela": "Entrada + parcelas a partir de R$ 1.118*"
    },
    {
        "link": "https://www.seminovosmovida.com.br/veiculo/detalhe/Hatch/Fiat/Argo/1222050",
        "title": "Fiat Argo",
        "version": "Drive 1.0 6v Flex",
        "details": "2024/2025 • 48.652 KM • Recife Caxangá, PE",
        "old_price": null,
        "new_price": "R$ 75.500",
        "parcela": "Entrada + parcelas a partir de R$ 1.118*"
    },
    {
        "link": "https://www.seminovosmovida.com.br/veiculo/detalhe/Sedan/Fiat/Cronos/990536",
        "title": "Fiat Cronos",
        "version": "Drive 1.0 6v Flex",
        "details": "2023/2024 • 68.039 KM • Porto Alegre Sarandi, RS",
        "old_price": null,
        "new_price": "R$ 75.500",
        "parcela": "Entrada + parcelas a partir de R$ 1.118*"
    },
    {
        "link": "https://www.seminovosmovida.com.br/veiculo/detalhe/Hatch/Volkswagen/Polo/1039922",
        "title": "Volkswagen Polo",
        "version": "Track 1.0 Flex 12v 5p",
        "details": "2023/2024 • 59.645 KM • Porto Alegre Ipiranga, RS",
        "old_price": null,
        "new_price": "R$ 75.500",
        "parcela": "Entrada + parcelas a partir de R$ 1.118*"
    },
    {
        "link": "https://www.seminovosmovida.com.br/veiculo/detalhe/Hatch/Fiat/Argo/1222163",
        "title": "Fiat Argo",
        "version": "Drive 1.0 6v Flex",
        "details": "2024/2025 • 47.145 KM • Recife Espinheiro, PE",
        "old_price": null,
        "new_price": "R$ 75.500",
        "parcela": "Entrada + parcelas a partir de R$ 1.118*"
    },
    {
        "link": "https://www.seminovosmovida.com.br/veiculo/detalhe/Hatch/Fiat/Argo/1222099",
        "title": "Fiat Argo",
        "version": "Drive 1.0 6v Flex",
        "details": "2024/2025 • 49.305 KM • Recife Espinheiro, PE",
        "old_price": null,
        "new_price": "R$ 75.500",
        "parcela": "Entrada + parcelas a partir de R$ 1.118*"
    },
    {
        "link": "https://www.seminovosmovida.com.br/veiculo/detalhe/Sedan/Fiat/Cronos/1002187",
        "title": "Fiat Cronos",
        "version": "Drive 1.0 6v Flex",
        "details": "2023/2024 • 73.971 KM • Porto Alegre Sarandi, RS",
        "old_price": null,
        "new_price": "R$ 75.500",
        "parcela": "Entrada + parcelas a partir de R$ 1.118*"
    },
    {
        "link": "https://www.seminovosmovida.com.br/veiculo/detalhe/Sedan/Fiat/Cronos/1040971",
        "title": "Fiat Cronos",
        "version": "Drive 1.0 6v Flex",
        "details": "2023/2024 • 75.886 KM • Porto Alegre Sarandi, RS",
        "old_price": null,
        "new_price": "R$ 75.500",
        "parcela": "Entrada + parcelas a partir de R$ 1.118*"
    },
    {
        "link": "https://www.seminovosmovida.com.br/veiculo/detalhe/Hatch/Volkswagen/Polo/1144818",
        "title": "Volkswagen Polo",
        "version": "Track 1.0 Flex 12v 5p",
        "details": "2024/2025 • 51.146 KM • Santo André, SP",
        "old_price": null,
        "new_price": "R$ 75.500",
        "parcela": "Entrada + parcelas a partir de R$ 1.118*"
    },
    {
        "link": "https://www.seminovosmovida.com.br/veiculo/detalhe/Sedan/Fiat/Cronos/1041719",
        "title": "Fiat Cronos",
        "version": "Drive 1.0 6v Flex",
        "details": "2023/2024 • 77.707 KM • Porto Alegre Sarandi, RS",
        "old_price": null,
        "new_price": "R$ 75.500",
        "parcela": "Entrada + parcelas a partir de R$ 1.118*"
    },
    {
        "link": "https://www.seminovosmovida.com.br/veiculo/detalhe/Hatch/Volkswagen/Polo/1152822",
        "title": "Volkswagen Polo",
        "version": "Track 1.0 Flex 12v 5p",
        "details": "2024/2025 • 55.668 KM • Ribeirão Preto, SP",
        "old_price": null,
        "new_price": "R$ 75.500",
        "parcela": "Entrada + parcelas a partir de R$ 1.118*"
    },
    {
        "link": "https://www.seminovosmovida.com.br/veiculo/detalhe/Sedan/Fiat/Cronos/1001283",
        "title": "Fiat Cronos",
        "version": "Drive 1.0 6v Flex",
        "details": "2023/2024 • 74.851 KM • Porto Alegre Sarandi, RS",
        "old_price": null,
        "new_price": "R$ 75.500",
        "parcela": "Entrada + parcelas a partir de R$ 1.118*"
    },
    {
        "link": "https://www.seminovosmovida.com.br/veiculo/detalhe/Hatch/Volkswagen/Polo/1152812",
        "title": "Volkswagen Polo",
        "version": "Track 1.0 Flex 12v 5p",
        "details": "2024/2025 • 52.998 KM • Americana, SP",
        "old_price": null,
        "new_price": "R$ 75.500",
        "parcela": "Entrada + parcelas a partir de R$ 1.118*"
    },
    {
        "link": "https://www.seminovosmovida.com.br/veiculo/detalhe/Sedan/Fiat/Cronos/1002182",
        "title": "Fiat Cronos",
        "version": "Drive 1.0 6v Flex",
        "details": "2023/2024 • 73.848 KM • Porto Alegre Sarandi, RS",
        "old_price": null,
        "new_price": "R$ 75.500",
        "parcela": "Entrada + parcelas a partir de R$ 1.118*"
    },
    {
        "link": "https://www.seminovosmovida.com.br/veiculo/detalhe/Hatch/Hyundai/Hb20/1174221",
        "title": "Hyundai Hb20",
        "version": "Comfort Plus 1.0 Flex 12v Mec.",
        "details": "2024/2025 • 56.649 KM • Blumenau, SC",
        "old_price": null,
        "new_price": "R$ 75.500",
        "parcela": "Entrada + parcelas a partir de R$ 1.118*"
    },
    {
        "link": "https://www.seminovosmovida.com.br/veiculo/detalhe/Hatch/Fiat/Argo/1244137",
        "title": "Fiat Argo",
        "version": "Drive 1.0 6v Flex",
        "details": "2025/2025 • 47.541 KM • Uberlândia, MG",
        "old_price": null,
        "new_price": "R$ 75.500",
        "parcela": "Entrada + parcelas a partir de R$ 1.118*"
    },
    {
        "link": "https://www.seminovosmovida.com.br/veiculo/detalhe/Hatch/Fiat/Argo/1244164",
        "title": "Fiat Argo",
        "version": "Drive 1.0 6v Flex",
        "details": "2025/2025 • 42.579 KM • São Paulo Gastão Vidigal, SP",
        "old_price": null,
        "new_price": "R$ 75.500",
        "parcela": "Entrada + parcelas a partir de R$ 1.118*"
    },
    {
        "link": "https://www.seminovosmovida.com.br/veiculo/detalhe/Hatch/Hyundai/Hb20/1207241",
        "title": "Hyundai Hb20",
        "version": "Comfort Plus 1.0 Flex 12v Mec.",
        "details": "2024/2025 • 59.215 KM • Itajaí, SC",
        "old_price": null,
        "new_price": "R$ 75.500",
        "parcela": "Entrada + parcelas a partir de R$ 1.118*"
    },
    {
        "link": "https://www.seminovosmovida.com.br/veiculo/detalhe/Hatch/Volkswagen/Polo/1144663",
        "title": "Volkswagen Polo",
        "version": "Track 1.0 Flex 12v 5p",
        "details": "2024/2025 • 52.498 KM • São Paulo São Miguel, SP",
        "old_price": null,
        "new_price": "R$ 75.500",
        "parcela": "Entrada + parcelas a partir de R$ 1.118*"
    },
    {
        "link": "https://www.seminovosmovida.com.br/veiculo/detalhe/Hatch/Fiat/Argo/1244150",
        "title": "Fiat Argo",
        "version": "Drive 1.0 6v Flex",
        "details": "2025/2025 • 47.805 KM • Uberlândia, MG",
        "old_price": null,
        "new_price": "R$ 75.500",
        "parcela": "Entrada + parcelas a partir de R$ 1.118*"
    },
    {
        "link": "https://www.seminovosmovida.com.br/veiculo/detalhe/Hatch/Fiat/Argo/1212280",
        "title": "Fiat Argo",
        "version": "Drive 1.0 6v Flex",
        "details": "2024/2025 • 47.789 KM • São Paulo Miguel Estefano, SP",
        "old_price": null,
        "new_price": "R$ 75.500",
        "parcela": "Entrada + parcelas a partir de R$ 1.118*"
    },
    {
        "link": "https://www.seminovosmovida.com.br/veiculo/detalhe/Hatch/Volkswagen/Polo/1072787",
        "title": "Volkswagen Polo",
        "version": "Track 1.0 Flex 12v 5p",
        "details": "2024/2024 • 55.119 KM • Blumenau, SC",
        "old_price": null,
        "new_price": "R$ 75.500",
        "parcela": "Entrada + parcelas a partir de R$ 1.118*"
    },
    {
        "link": "https://www.seminovosmovida.com.br/veiculo/detalhe/Pickup/Fiat/Strada/843552",
        "title": "Fiat Strada",
        "version": "Endurance 1.4 Flex 8v Cs Plus",
        "details": "2022/2022 • 37.945 KM • Betim, MG",
        "old_price": null,
        "new_price": "R$ 75.600",
        "parcela": "Entrada + parcelas a partir de R$ 1.119*"
    },
    {
        "link": "https://www.seminovosmovida.com.br/veiculo/detalhe/Hatch/Volkswagen/Polo/1033479",
        "title": "Volkswagen Polo",
        "version": "1.0 Mpi Flex 12v 5p",
        "details": "2023/2024 • 56.665 KM • Salvador Paralela, BA",
        "old_price": null,
        "new_price": "R$ 75.600",
        "parcela": "Entrada + parcelas a partir de R$ 1.119*"
    },
    {
        "link": "https://www.seminovosmovida.com.br/veiculo/detalhe/Hatch/Volkswagen/Polo/1172676",
        "title": "Volkswagen Polo",
        "version": "Track 1.0 Flex 12v 5p",
        "details": "2024/2025 • 71.957 KM • Auto Shopping Fórmula, MT",
        "old_price": null,
        "new_price": "R$ 75.600",
        "parcela": "Entrada + parcelas a partir de R$ 1.119*"
    },
    {
        "link": "https://www.seminovosmovida.com.br/veiculo/detalhe/Hatch/Volkswagen/Polo/1149928",
        "title": "Volkswagen Polo",
        "version": "Track 1.0 Flex 12v 5p",
        "details": "2024/2025 • 71.962 KM • Betim, MG",
        "old_price": null,
        "new_price": "R$ 75.600",
        "parcela": "Entrada + parcelas a partir de R$ 1.119*"
    },
    {
        "link": "https://www.seminovosmovida.com.br/veiculo/detalhe/Sedan/Renault/Logan/1193565",
        "title": "Renault Logan",
        "version": "Zen Flex 1.0 12v 4p Mec.",
        "details": "2024/2025 • 27.822 KM • Recife Caxangá, PE",
        "old_price": null,
        "new_price": "R$ 75.700",
        "parcela": "Entrada + parcelas a partir de R$ 1.121*"
    },
    {
        "link": "https://www.seminovosmovida.com.br/veiculo/detalhe/Pickup/Volkswagen/Saveiro/1108513",
        "title": "Volkswagen Saveiro",
        "version": "Robust 1.6 Total Flex 16v",
        "details": "2024/2024 • 32.106 KM • Canoas, RS",
        "old_price": null,
        "new_price": "R$ 75.700",
        "parcela": "Entrada + parcelas a partir de R$ 1.121*"
    },
    {
        "link": "https://www.seminovosmovida.com.br/veiculo/detalhe/Hatch/Hyundai/Hb20/1167812",
        "title": "Hyundai Hb20",
        "version": "Comfort Plus 1.0 Flex 12v Mec.",
        "details": "2024/2025 • 24.992 KM • Manaus, AM",
        "old_price": null,
        "new_price": "R$ 75.700",
        "parcela": "Entrada + parcelas a partir de R$ 1.121*"
    },
    {
        "link": "https://www.seminovosmovida.com.br/veiculo/detalhe/Hatch/Hyundai/Hb20/1211653",
        "title": "Hyundai Hb20",
        "version": "Comfort Plus 1.0 Flex 12v Mec.",
        "details": "2024/2025 • 75.793 KM • Auto Shopping Lauro de Freitas, BA",
        "old_price": null,
        "new_price": "R$ 75.700",
        "parcela": "Entrada + parcelas a partir de R$ 1.121*"
    },
    {
        "link": "https://www.seminovosmovida.com.br/veiculo/detalhe/Sedan/Renault/Logan/1180584",
        "title": "Renault Logan",
        "version": "Zen Flex 1.0 12v 4p Mec.",
        "details": "2024/2025 • 21.632 KM • Rio de Janeiro Barra da Tijuca, RJ",
        "old_price": null,
        "new_price": "R$ 75.700",
        "parcela": "Entrada + parcelas a partir de R$ 1.121*"
    },
    {
        "link": "https://www.seminovosmovida.com.br/veiculo/detalhe/Pickup/Volkswagen/Saveiro/1108502",
        "title": "Volkswagen Saveiro",
        "version": "Robust 1.6 Total Flex 16v",
        "details": "2024/2024 • 33.061 KM • Canoas, RS",
        "old_price": null,
        "new_price": "R$ 75.700",
        "parcela": "Entrada + parcelas a partir de R$ 1.121*"
    },
    {
        "link": "https://www.seminovosmovida.com.br/veiculo/detalhe/Hatch/Volkswagen/Polo/1034114",
        "title": "Volkswagen Polo",
        "version": "Track 1.0 Flex 12v 5p",
        "details": "2023/2024 • 58.826 KM • Auto Shopping Rodrigues, BA",
        "old_price": null,
        "new_price": "R$ 75.700",
        "parcela": "Entrada + parcelas a partir de R$ 1.121*"
    },
    {
        "link": "https://www.seminovosmovida.com.br/veiculo/detalhe/Hatch/Hyundai/Hb20/1176634",
        "title": "Hyundai Hb20",
        "version": "Comfort Plus 1.0 Flex 12v Mec.",
        "details": "2024/2025 • 56.362 KM • Taubaté, SP",
        "old_price": null,
        "new_price": "R$ 75.700",
        "parcela": "Entrada + parcelas a partir de R$ 1.121*"
    },
    {
        "link": "https://www.seminovosmovida.com.br/veiculo/detalhe/Pickup/Volkswagen/Saveiro/1106977",
        "title": "Volkswagen Saveiro",
        "version": "Robust 1.6 Total Flex 16v",
        "details": "2024/2024 • 48.504 KM • Rio de Janeiro Vila Valqueire, RJ",
        "old_price": null,
        "new_price": "R$ 75.800",
        "parcela": "Entrada + parcelas a partir de R$ 1.122*"
    },
    {
        "link": "https://www.seminovosmovida.com.br/veiculo/detalhe/Pickup/Volkswagen/Saveiro/1105972",
        "title": "Volkswagen Saveiro",
        "version": "Robust 1.6 Total Flex 16v",
        "details": "2024/2024 • 40.179 KM • Rio de Janeiro Vila Valqueire, RJ",
        "old_price": null,
        "new_price": "R$ 75.800",
        "parcela": "Entrada + parcelas a partir de R$ 1.122*"
    },
    {
        "link": "https://www.seminovosmovida.com.br/veiculo/detalhe/Hatch/Volkswagen/Polo/1214428",
        "title": "Volkswagen Polo",
        "version": "Track 1.0 Flex 12v 5p",
        "details": "2024/2025 • 73.692 KM • Auto Shopping Shopping Car, RJ",
        "old_price": null,
        "new_price": "R$ 75.800",
        "parcela": "Entrada + parcelas a partir de R$ 1.122*"
    },
    {
        "link": "https://www.seminovosmovida.com.br/veiculo/detalhe/Pickup/Volkswagen/Saveiro/1108453",
        "title": "Volkswagen Saveiro",
        "version": "Robust 1.6 Total Flex 16v",
        "details": "2024/2024 • 44.069 KM • Rio de Janeiro Campo Grande, RJ",
        "old_price": null,
        "new_price": "R$ 75.800",
        "parcela": "Entrada + parcelas a partir de R$ 1.122*"
    },
    {
        "link": "https://www.seminovosmovida.com.br/veiculo/detalhe/Pickup/Volkswagen/Saveiro/1027065",
        "title": "Volkswagen Saveiro",
        "version": "Robust 1.6 Total Flex 16v",
        "details": "2023/2024 • 47.528 KM • Contagem Babita Camargo, MG",
        "old_price": null,
        "new_price": "R$ 75.800",
        "parcela": "Entrada + parcelas a partir de R$ 1.122*"
    },
    {
        "link": "https://www.seminovosmovida.com.br/veiculo/detalhe/Pickup/Volkswagen/Saveiro/1106218",
        "title": "Volkswagen Saveiro",
        "version": "Robust 1.6 Total Flex 16v",
        "details": "2024/2024 • 46.342 KM • Nova Iguaçu, RJ",
        "old_price": null,
        "new_price": "R$ 75.800",
        "parcela": "Entrada + parcelas a partir de R$ 1.122*"
    },
    {
        "link": "https://www.seminovosmovida.com.br/veiculo/detalhe/Pickup/Volkswagen/Saveiro/1106598",
        "title": "Volkswagen Saveiro",
        "version": "Robust 1.6 Total Flex 16v",
        "details": "2024/2024 • 42.425 KM • Nova Iguaçu, RJ",
        "old_price": null,
        "new_price": "R$ 75.800",
        "parcela": "Entrada + parcelas a partir de R$ 1.122*"
    },
    {
        "link": "https://www.seminovosmovida.com.br/veiculo/detalhe/Pickup/Volkswagen/Saveiro/1105787",
        "title": "Volkswagen Saveiro",
        "version": "Robust 1.6 Total Flex 16v",
        "details": "2024/2024 • 41.275 KM • Rio de Janeiro Barra da Tijuca, RJ",
        "old_price": null,
        "new_price": "R$ 75.800",
        "parcela": "Entrada + parcelas a partir de R$ 1.122*"
    },
    {
        "link": "https://www.seminovosmovida.com.br/veiculo/detalhe/Pickup/Volkswagen/Saveiro/1112127",
        "title": "Volkswagen Saveiro",
        "version": "Robust 1.6 Total Flex 16v",
        "details": "2024/2024 • 44.467 KM • Rio de Janeiro Recreio dos Bandeirantes, RJ",
        "old_price": null,
        "new_price": "R$ 75.800",
        "parcela": "Entrada + parcelas a partir de R$ 1.122*"
    },
    {
        "link": "https://www.seminovosmovida.com.br/veiculo/detalhe/Pickup/Volkswagen/Saveiro/1106760",
        "title": "Volkswagen Saveiro",
        "version": "Robust 1.6 Total Flex 16v",
        "details": "2024/2024 • 42.828 KM • Joinville, SC",
        "old_price": null,
        "new_price": "R$ 75.800",
        "parcela": "Entrada + parcelas a partir de R$ 1.122*"
    },
    {
        "link": "https://www.seminovosmovida.com.br/veiculo/detalhe/Hatch/Chevrolet/Onix/1231834",
        "title": "Chevrolet Onix",
        "version": "Hatch Lt 1.0 12v Flex 5p Mec.",
        "details": "2024/2025 • 45.775 KM • Fortaleza Av. Santos Dumont, CE",
        "old_price": null,
        "new_price": "R$ 75.800",
        "parcela": "Entrada + parcelas a partir de R$ 1.122*"
    },
    {
        "link": "https://www.seminovosmovida.com.br/veiculo/detalhe/Sedan/Fiat/Cronos/1042746",
        "title": "Fiat Cronos",
        "version": "Drive 1.0 6v Flex",
        "details": "2023/2024 • 75.424 KM • São Paulo Vila Guilherme, SP",
        "old_price": null,
        "new_price": "R$ 75.900",
        "parcela": "Entrada + parcelas a partir de R$ 1.124*"
    },
    {
        "link": "https://www.seminovosmovida.com.br/veiculo/detalhe/Sedan/Fiat/Cronos/985764",
        "title": "Fiat Cronos",
        "version": "Drive 1.0 6v Flex",
        "details": "2023/2024 • 92.602 KM • São Carlos, SP",
        "old_price": null,
        "new_price": "R$ 75.900",
        "parcela": "Entrada + parcelas a partir de R$ 1.124*"
    },
    {
        "link": "https://www.seminovosmovida.com.br/veiculo/detalhe/Hatch/Volkswagen/Polo/1080841",
        "title": "Volkswagen Polo",
        "version": "Track 1.0 Flex 12v 5p",
        "details": "2024/2024 • 49.905 KM • Várzea Grande, MT",
        "old_price": null,
        "new_price": "R$ 75.900",
        "parcela": "Entrada + parcelas a partir de R$ 1.124*"
    },
    {
        "link": "https://www.seminovosmovida.com.br/veiculo/detalhe/Hatch/Hyundai/Hb20/1207085",
        "title": "Hyundai Hb20",
        "version": "Comfort Plus 1.0 Flex 12v Mec.",
        "details": "2024/2025 • 40.031 KM • São José dos Pinhais, PR",
        "old_price": null,
        "new_price": "R$ 75.900",
        "parcela": "Entrada + parcelas a partir de R$ 1.124*"
    },
    {
        "link": "https://www.seminovosmovida.com.br/veiculo/detalhe/Hatch/Volkswagen/Polo/1100135",
        "title": "Volkswagen Polo",
        "version": "Track 1.0 Flex 12v 5p",
        "details": "2024/2024 • 46.054 KM • Canoas, RS",
        "old_price": null,
        "new_price": "R$ 75.900",
        "parcela": "Entrada + parcelas a partir de R$ 1.124*"
    },
    {
        "link": "https://www.seminovosmovida.com.br/veiculo/detalhe/Sedan/Fiat/Cronos/1040891",
        "title": "Fiat Cronos",
        "version": "Drive 1.0 6v Flex",
        "details": "2023/2024 • 82.026 KM • São Paulo São Miguel, SP",
        "old_price": null,
        "new_price": "R$ 75.900",
        "parcela": "Entrada + parcelas a partir de R$ 1.124*"
    },
    {
        "link": "https://www.seminovosmovida.com.br/veiculo/detalhe/Hatch/Volkswagen/Polo/1156665",
        "title": "Volkswagen Polo",
        "version": "Track 1.0 Flex 12v 5p",
        "details": "2024/2025 • 69.918 KM • Serra, ES",
        "old_price": null,
        "new_price": "R$ 75.900",
        "parcela": "Entrada + parcelas a partir de R$ 1.124*"
    },
    {
        "link": "https://www.seminovosmovida.com.br/veiculo/detalhe/Sedan/Fiat/Cronos/991148",
        "title": "Fiat Cronos",
        "version": "Drive 1.0 6v Flex",
        "details": "2023/2024 • 78.245 KM • São Paulo Radial Leste, SP",
        "old_price": null,
        "new_price": "R$ 75.900",
        "parcela": "Entrada + parcelas a partir de R$ 1.124*"
    },
    {
        "link": "https://www.seminovosmovida.com.br/veiculo/detalhe/Pickup/Volkswagen/Saveiro/1000675",
        "title": "Volkswagen Saveiro",
        "version": "Robust 1.6 Total Flex 16v",
        "details": "2023/2024 • 42.335 KM • São Paulo Vila Carrão, SP",
        "old_price": null,
        "new_price": "R$ 76.000",
        "parcela": "Entrada + parcelas a partir de R$ 1.125*"
    },
    {
        "link": "https://www.seminovosmovida.com.br/veiculo/detalhe/Hatch/Volkswagen/Polo/1062717",
        "title": "Volkswagen Polo",
        "version": "Track 1.0 Flex 12v 5p",
        "details": "2023/2024 • 37.275 KM • São Paulo Miguel Estefano, SP",
        "old_price": null,
        "new_price": "R$ 76.000",
        "parcela": "Entrada + parcelas a partir de R$ 1.125*"
    },
    {
        "link": "https://www.seminovosmovida.com.br/veiculo/detalhe/Pickup/Volkswagen/Saveiro/1106664",
        "title": "Volkswagen Saveiro",
        "version": "Robust 1.6 Total Flex 16v",
        "details": "2024/2024 • 44.043 KM • Piracicaba, SP",
        "old_price": null,
        "new_price": "R$ 76.000",
        "parcela": "Entrada + parcelas a partir de R$ 1.125*"
    },
    {
        "link": "https://www.seminovosmovida.com.br/veiculo/detalhe/Pickup/Volkswagen/Saveiro/1105903",
        "title": "Volkswagen Saveiro",
        "version": "Robust 1.6 Total Flex 16v",
        "details": "2024/2024 • 41.900 KM • Canoas, RS",
        "old_price": null,
        "new_price": "R$ 76.000",
        "parcela": "Entrada + parcelas a partir de R$ 1.125*"
    },
    {
        "link": "https://www.seminovosmovida.com.br/veiculo/detalhe/Hatch/Hyundai/Hb20/1176702",
        "title": "Hyundai Hb20",
        "version": "Comfort Plus 1.0 Flex 12v Mec.",
        "details": "2024/2025 • 44.937 KM • São Luís, MA",
        "old_price": null,
        "new_price": "R$ 76.000",
        "parcela": "Entrada + parcelas a partir de R$ 1.125*"
    },
    {
        "link": "https://www.seminovosmovida.com.br/veiculo/detalhe/Hatch/Fiat/Argo/1127734",
        "title": "Fiat Argo",
        "version": "1.0 6v Flex",
        "details": "2024/2025 • 18.339 KM • Belo Horizonte Carlos Luz, MG",
        "old_price": null,
        "new_price": "R$ 76.000",
        "parcela": "Entrada + parcelas a partir de R$ 1.125*"
    },
    {
        "link": "https://www.seminovosmovida.com.br/veiculo/detalhe/Hatch/Volkswagen/Polo/1071482",
        "title": "Volkswagen Polo",
        "version": "Track 1.0 Flex 12v 5p",
        "details": "2024/2024 • 41.553 KM • Belo Horizonte Raja, MG",
        "old_price": null,
        "new_price": "R$ 76.000",
        "parcela": "Entrada + parcelas a partir de R$ 1.125*"
    },
    {
        "link": "https://www.seminovosmovida.com.br/veiculo/detalhe/Pickup/Volkswagen/Saveiro/1105867",
        "title": "Volkswagen Saveiro",
        "version": "Robust 1.6 Total Flex 16v",
        "details": "2024/2024 • 41.395 KM • Auto Shopping Arena Motors, SP",
        "old_price": null,
        "new_price": "R$ 76.000",
        "parcela": "Entrada + parcelas a partir de R$ 1.125*"
    },
    {
        "link": "https://www.seminovosmovida.com.br/veiculo/detalhe/Hatch/Citroen/C3/1218966",
        "title": "Citroen C3",
        "version": "Live Pack 1.0 Flex 6v 5p Mec.",
        "details": "2024/2025 • 25.325 KM • Rio de Janeiro Intendente Magalhães, RJ",
        "old_price": null,
        "new_price": "R$ 76.000",
        "parcela": "Entrada + parcelas a partir de R$ 1.125*"
    },
    {
        "link": "https://www.seminovosmovida.com.br/veiculo/detalhe/Pickup/Volkswagen/Saveiro/1106167",
        "title": "Volkswagen Saveiro",
        "version": "Robust 1.6 Total Flex 16v",
        "details": "2024/2024 • 30.052 KM • São Paulo Eliseu de Almeida, SP",
        "old_price": null,
        "new_price": "R$ 76.000",
        "parcela": "Entrada + parcelas a partir de R$ 1.125*"
    },
    {
        "link": "https://www.seminovosmovida.com.br/veiculo/detalhe/Pickup/Volkswagen/Saveiro/1106020",
        "title": "Volkswagen Saveiro",
        "version": "Robust 1.6 Total Flex 16v",
        "details": "2024/2024 • 44.630 KM • São José dos Campos, SP",
        "old_price": null,
        "new_price": "R$ 76.000",
        "parcela": "Entrada + parcelas a partir de R$ 1.125*"
    },
    {
        "link": "https://www.seminovosmovida.com.br/veiculo/detalhe/Pickup/Volkswagen/Saveiro/1106343",
        "title": "Volkswagen Saveiro",
        "version": "Robust 1.6 Total Flex 16v",
        "details": "2024/2024 • 47.222 KM • São Leopoldo, RS",
        "old_price": null,
        "new_price": "R$ 76.000",
        "parcela": "Entrada + parcelas a partir de R$ 1.125*"
    },
    {
        "link": "https://www.seminovosmovida.com.br/veiculo/detalhe/Pickup/Volkswagen/Saveiro/1027015",
        "title": "Volkswagen Saveiro",
        "version": "Robust 1.6 Total Flex 16v",
        "details": "2023/2024 • 45.148 KM • Canoas, RS",
        "old_price": null,
        "new_price": "R$ 76.000",
        "parcela": "Entrada + parcelas a partir de R$ 1.125*"
    },
    {
        "link": "https://www.seminovosmovida.com.br/veiculo/detalhe/Hatch/Citroen/C3/1174823",
        "title": "Citroen C3",
        "version": "Live Pack 1.0 Flex 6v 5p Mec.",
        "details": "2024/2025 • 24.466 KM • Rio de Janeiro Vila Valqueire, RJ",
        "old_price": null,
        "new_price": "R$ 76.000",
        "parcela": "Entrada + parcelas a partir de R$ 1.125*"
    },
    {
        "link": "https://www.seminovosmovida.com.br/veiculo/detalhe/Pickup/Volkswagen/Saveiro/1105799",
        "title": "Volkswagen Saveiro",
        "version": "Robust 1.6 Total Flex 16v",
        "details": "2024/2024 • 42.522 KM • Canoas, RS",
        "old_price": null,
        "new_price": "R$ 76.000",
        "parcela": "Entrada + parcelas a partir de R$ 1.125*"
    }
]